{
   "title": "Portuguese (Portugal)",
   "address": {
      "city_prefix": [
         "Câmara de",
         "Caldas da",
         "Oliveira de",
         "Vila Nova de",
         "São",
         "Vale de"
      ],
      "city_suffix": [
         "do Douro",
         "do Minho",
         "do Hospital",
         "de Ferreira",
         "da Feira",
         "do Sul"
      ],
      "country": [
         "Afeganistão",
         "África do Sul",
         "Akrotiri",
         "Albânia",
         "Alemanha",
         "Andorra",
         "Angola",
         "Anguila",
         "Antárctida",
         "Antígua e Barbuda",
         "Antilhas Neerlandesas",
         "Arábia Saudita",
         "Arctic Ocean",
         "Argélia",
         "Argentina",
         "Arménia",
         "Aruba",
         "Ashmore and Cartier Islands",
         "Atlantic Ocean",
         "Austrália",
         "Áustria",
         "Azerbaijão",
         "Baamas",
         "Bangladeche",
         "Barbados",
         "Barém",
         "Bélgica",
         "Belize",
         "Benim",
         "Bermudas",
         "Bielorrússia",
         "Birmânia",
         "Bolívia",
         "Bósnia e Herzegovina",
         "Botsuana",
         "Brasil",
         "Brunei",
         "Bulgária",
         "Burquina Faso",
         "Burúndi",
         "Butão",
         "Cabo Verde",
         "Camarões",
         "Camboja",
         "Canadá",
         "Catar",
         "Cazaquistão",
         "Chade",
         "Chile",
         "China",
         "Chipre",
         "Clipperton Island",
         "Colômbia",
         "Comores",
         "Congo-Brazzaville",
         "Congo-Kinshasa",
         "Coral Sea Islands",
         "Coreia do Norte",
         "Coreia do Sul",
         "Costa do Marfim",
         "Costa Rica",
         "Croácia",
         "Cuba",
         "Dhekelia",
         "Dinamarca",
         "Domínica",
         "Egipto",
         "Emiratos Árabes Unidos",
         "Equador",
         "Eritreia",
         "Eslováquia",
         "Eslovénia",
         "Espanha",
         "Estados Unidos",
         "Estónia",
         "Etiópia",
         "Faroé",
         "Fiji",
         "Filipinas",
         "Finlândia",
         "França",
         "Gabão",
         "Gâmbia",
         "Gana",
         "Faixa de Gaza",
         "Geórgia",
         "Geórgia do Sul e Sandwich do Sul",
         "Gibraltar",
         "Granada",
         "Grécia",
         "Gronelândia",
         "Guame",
         "Guatemala",
         "Guernsey",
         "Guiana",
         "Guiné",
         "Guiné Equatorial",
         "Guiné-Bissau",
         "Haiti",
         "Honduras",
         "Hong Kong",
         "Hungria",
         "Iémen",
         "Ilha Bouvet",
         "Ilha do Natal",
         "Ilha Norfolk",
         "Ilhas Caimão",
         "Ilhas Cook",
         "Ilhas dos Cocos",
         "Ilhas Falkland",
         "Ilhas Heard e McDonald",
         "Ilhas Marshall",
         "Ilhas Salomão",
         "Ilhas Turcas e Caicos",
         "Ilhas Virgens Americanas",
         "Ilhas Virgens Britânicas",
         "Índia",
         "Indian Ocean",
         "Indonésia",
         "Irão",
         "Iraque",
         "Irlanda",
         "Islândia",
         "Israel",
         "Itália",
         "Jamaica",
         "Jan Mayen",
         "Japão",
         "Jersey",
         "Jibuti",
         "Jordânia",
         "Kuwait",
         "Laos",
         "Lesoto",
         "Letónia",
         "Líbano",
         "Libéria",
         "Líbia",
         "Listenstaine",
         "Lituânia",
         "Luxemburgo",
         "Macau",
         "Macedónia",
         "Madagáscar",
         "Malásia",
         "Malávi",
         "Maldivas",
         "Mali",
         "Malta",
         "Man, Isle of",
         "Marianas do Norte",
         "Marrocos",
         "Maurícia",
         "Mauritânia",
         "Mayotte",
         "México",
         "Micronésia",
         "Moçambique",
         "Moldávia",
         "Mónaco",
         "Mongólia",
         "Monserrate",
         "Montenegro",
         "Mundo",
         "Namíbia",
         "Nauru",
         "Navassa Island",
         "Nepal",
         "Nicarágua",
         "Níger",
         "Nigéria",
         "Niue",
         "Noruega",
         "Nova Caledónia",
         "Nova Zelândia",
         "Omã",
         "Pacific Ocean",
         "Países Baixos",
         "Palau",
         "Panamá",
         "Papua-Nova Guiné",
         "Paquistão",
         "Paracel Islands",
         "Paraguai",
         "Peru",
         "Pitcairn",
         "Polinésia Francesa",
         "Polónia",
         "Porto Rico",
         "Portugal",
         "Quénia",
         "Quirguizistão",
         "Quiribáti",
         "Reino Unido",
         "República Centro-Africana",
         "República Checa",
         "República Dominicana",
         "Roménia",
         "Ruanda",
         "Rússia",
         "Salvador",
         "Samoa",
         "Samoa Americana",
         "Santa Helena",
         "Santa Lúcia",
         "São Cristóvão e Neves",
         "São Marinho",
         "São Pedro e Miquelon",
         "São Tomé e Príncipe",
         "São Vicente e Granadinas",
         "Sara Ocidental",
         "Seicheles",
         "Senegal",
         "Serra Leoa",
         "Sérvia",
         "Singapura",
         "Síria",
         "Somália",
         "Southern Ocean",
         "Spratly Islands",
         "Sri Lanca",
         "Suazilândia",
         "Sudão",
         "Suécia",
         "Suíça",
         "Suriname",
         "Svalbard e Jan Mayen",
         "Tailândia",
         "Taiwan",
         "Tajiquistão",
         "Tanzânia",
         "Território Britânico do Oceano Índico",
         "Territórios Austrais Franceses",
         "Timor Leste",
         "Togo",
         "Tokelau",
         "Tonga",
         "Trindade e Tobago",
         "Tunísia",
         "Turquemenistão",
         "Turquia",
         "Tuvalu",
         "Ucrânia",
         "Uganda",
         "União Europeia",
         "Uruguai",
         "Usbequistão",
         "Vanuatu",
         "Vaticano",
         "Venezuela",
         "Vietname",
         "Wake Island",
         "Wallis e Futuna",
         "West Bank",
         "Zâmbia",
         "Zimbabué"
      ],
      "building_number": [
         "#####",
         "####",
         "###"
      ],
      "street_suffix": [
         "Rua",
         "Avenida",
         "Travessa",
         "Ponte",
         "Alameda",
         "Marginal",
         "Viela",
         "Estrada"
      ],
      "secondary_address": [
         "Apto. ###",
         "Casa #",
         "Lote ##",
         "Bloco ##"
      ],
      "postcode": [
         "#####",
         "#####-###"
      ],
      "state": [
         "Aveiro",
         "Beja",
         "Braga",
         "Bragança",
         "Castelo Branco",
         "Coimbra",
         "Évora",
         "Faro",
         "Guarda",
         "Leiria",
         "Lisboa",
         "Portalegre",
         "Porto",
         "Santarém",
         "Setúbal",
         "Viana do Castelo",
         "Vila Real",
         "Viseu"
      ],
      "state_abbr": [
         "NA"
      ],
      "default_country": [
         "Portugal"
      ]
   },
   "company": {
      "suffix": [
         "S.A.",
         "LTDA",
         "e Associados",
         "Comércio"
      ],
      "name": [
         "#{Name.last_name} #{suffix}",
         "#{Name.last_name}-#{Name.last_name}",
         "#{Name.last_name}, #{Name.last_name} e #{Name.last_name}"
      ]
   },
   "internet": {
      "free_email": [
         "gmail.com",
         "yahoo.com",
         "hotmail.com",
         "live.com",
         "sapo.pt",
         "iol.pt"
      ],
      "domain_suffix": [
         "pt",
         "com",
         "biz",
         "info",
         "name",
         "net",
         "org"
      ]
   },
   "lorem": {
      "words": [
         "alias",
         "consequatur",
         "aut",
         "perferendis",
         "sit",
         "voluptatem",
         "accusantium",
         "doloremque",
         "aperiam",
         "eaque",
         "ipsa",
         "quae",
         "ab",
         "illo",
         "inventore",
         "veritatis",
         "et",
         "quasi",
         "architecto",
         "beatae",
         "vitae",
         "dicta",
         "sunt",
         "explicabo",
         "aspernatur",
         "aut",
         "odit",
         "aut",
         "fugit",
         "sed",
         "quia",
         "consequuntur",
         "magni",
         "dolores",
         "eos",
         "qui",
         "ratione",
         "voluptatem",
         "sequi",
         "nesciunt",
         "neque",
         "dolorem",
         "ipsum",
         "quia",
         "dolor",
         "sit",
         "amet",
         "consectetur",
         "adipisci",
         "velit",
         "sed",
         "quia",
         "non",
         "numquam",
         "eius",
         "modi",
         "tempora",
         "incidunt",
         "ut",
         "labore",
         "et",
         "dolore",
         "magnam",
         "aliquam",
         "quaerat",
         "voluptatem",
         "ut",
         "enim",
         "ad",
         "minima",
         "veniam",
         "quis",
         "nostrum",
         "exercitationem",
         "ullam",
         "corporis",
         "nemo",
         "enim",
         "ipsam",
         "voluptatem",
         "quia",
         "voluptas",
         "sit",
         "suscipit",
         "laboriosam",
         "nisi",
         "ut",
         "aliquid",
         "ex",
         "ea",
         "commodi",
         "consequatur",
         "quis",
         "autem",
         "vel",
         "eum",
         "iure",
         "reprehenderit",
         "qui",
         "in",
         "ea",
         "voluptate",
         "velit",
         "esse",
         "quam",
         "nihil",
         "molestiae",
         "et",
         "iusto",
         "odio",
         "dignissimos",
         "ducimus",
         "qui",
         "blanditiis",
         "praesentium",
         "laudantium",
         "totam",
         "rem",
         "voluptatum",
         "deleniti",
         "atque",
         "corrupti",
         "quos",
         "dolores",
         "et",
         "quas",
         "molestias",
         "excepturi",
         "sint",
         "occaecati",
         "cupiditate",
         "non",
         "provident",
         "sed",
         "ut",
         "perspiciatis",
         "unde",
         "omnis",
         "iste",
         "natus",
         "error",
         "similique",
         "sunt",
         "in",
         "culpa",
         "qui",
         "officia",
         "deserunt",
         "mollitia",
         "animi",
         "id",
         "est",
         "laborum",
         "et",
         "dolorum",
         "fuga",
         "et",
         "harum",
         "quidem",
         "rerum",
         "facilis",
         "est",
         "et",
         "expedita",
         "distinctio",
         "nam",
         "libero",
         "tempore",
         "cum",
         "soluta",
         "nobis",
         "est",
         "eligendi",
         "optio",
         "cumque",
         "nihil",
         "impedit",
         "quo",
         "porro",
         "quisquam",
         "est",
         "qui",
         "minus",
         "id",
         "quod",
         "maxime",
         "placeat",
         "facere",
         "possimus",
         "omnis",
         "voluptas",
         "assumenda",
         "est",
         "omnis",
         "dolor",
         "repellendus",
         "temporibus",
         "autem",
         "quibusdam",
         "et",
         "aut",
         "consequatur",
         "vel",
         "illum",
         "qui",
         "dolorem",
         "eum",
         "fugiat",
         "quo",
         "voluptas",
         "nulla",
         "pariatur",
         "at",
         "vero",
         "eos",
         "et",
         "accusamus",
         "officiis",
         "debitis",
         "aut",
         "rerum",
         "necessitatibus",
         "saepe",
         "eveniet",
         "ut",
         "et",
         "voluptates",
         "repudiandae",
         "sint",
         "et",
         "molestiae",
         "non",
         "recusandae",
         "itaque",
         "earum",
         "rerum",
         "hic",
         "tenetur",
         "a",
         "sapiente",
         "delectus",
         "ut",
         "aut",
         "reiciendis",
         "voluptatibus",
         "maiores",
         "doloribus",
         "asperiores",
         "repellat"
      ]
   },
   "name": {
      "first_name": [
         "Áurea",
         "Ângelo",
         "Érica",
         "Íris",
         "Adriana",
         "Afonso",
         "Alícia",
         "Alexandra",
         "Alexandre",
         "Alice",
         "Amélia",
         "Ana",
         "André",
         "Andreia",
         "António",
         "Ariana",
         "Artur",
         "Bárbara",
         "Beatriz",
         "Benedita",
         "Benjamim",
         "Bernardo",
         "Bianca",
         "Brian",
         "Bruna",
         "Bruno",
         "César",
         "Caetana",
         "Camila",
         "Carlos",
         "Carlota",
         "Carminho",
         "Carolina",
         "Catarina",
         "Clara",
         "Constança",
         "Cristiano",
         "Débora",
         "Daniel",
         "Daniela",
         "David",
         "Diana",
         "Diego",
         "Dinis",
         "Diogo",
         "Duarte",
         "Edgar",
         "Eduarda",
         "Eduardo",
         "Ema",
         "Emanuel",
         "Enzo",
         "Eva",
         "Fábio",
         "Fabiana",
         "Fernando",
         "Filipa",
         "Filipe",
         "Francisca",
         "Francisco",
         "Frederico",
         "Gabriel",
         "Gabriela",
         "Gil",
         "Gonçalo",
         "Guilherme",
         "Gustavo",
         "Helena",
         "Henrique",
         "Hugo",
         "Iara",
         "Inês",
         "Irina",
         "Isaac",
         "Isabel",
         "Isabela",
         "Isac",
         "Isis",
         "Ismael",
         "Ivan",
         "Ivo",
         "Jéssica",
         "Júlia",
         "Jaime",
         "João",
         "Joana",
         "Joaquim",
         "Joel",
         "Jorge",
         "José",
         "Juliana",
         "Kévim",
         "Kelly",
         "Kevin",
         "Kyara",
         "Lara",
         "Laura",
         "Leandro",
         "Leonardo",
         "Leonor",
         "Letícia",
         "Lia",
         "Liliana",
         "Lisandro",
         "Lorena",
         "Lourenço",
         "Luís",
         "Luísa",
         "Luana",
         "Luca",
         "Lucas",
         "Luciana",
         "Luna",
         "Márcio",
         "Mário",
         "Mélanie",
         "Madalena",
         "Mafalda",
         "Maiara",
         "Manel",
         "Manuel",
         "Mara",
         "Marco",
         "Margarida",
         "Maria",
         "Mariana",
         "Marta",
         "Martim",
         "Mateus",
         "Matias",
         "Matilde",
         "Melissa",
         "Mia",
         "Micael",
         "Miguel",
         "Miriam",
         "Nádia",
         "Núria",
         "Naiara",
         "Nelson",
         "Nicole",
         "Noa",
         "Noah",
         "Nuno",
         "Paloma",
         "Patrícia",
         "Paulo",
         "Pedro",
         "Pilar",
         "Rúben",
         "Raúl",
         "Rafael",
         "Rafaela",
         "Raissa",
         "Raquel",
         "Renata",
         "Renato",
         "Ricardo",
         "Rita",
         "Rodrigo",
         "Rui",
         "Sérgio",
         "Salvador",
         "Samuel",
         "Sandro",
         "Santiago",
         "Sara",
         "Sebastião",
         "Simão",
         "Sofia",
         "Soraia",
         "Tatiana",
         "Teresa",
         "Tiago",
         "Tomás",
         "Tomé",
         "Vítor",
         "Valentim",
         "Valentina",
         "Vasco",
         "Vicente",
         "Victória",
         "Violeta",
         "Vitória",
         "William",
         "Wilson",
         "Xavier",
         "Yara",
         "Yasmin"
      ],
      "last_name": [
         "Silva",
         "Sousa",
         "Carvalho",
         "Santos",
         "Reis",
         "Xavier",
         "Franco",
         "Braga",
         "Macedo",
         "Batista",
         "Barros",
         "Morais",
         "Costa",
         "Pereira",
         "Carvalho",
         "Melo",
         "Saraiva",
         "Nogueira",
         "Oliveira",
         "Martins",
         "Moreira",
         "Albuquerque"
      ],
      "prefix": [
         "Sr.",
         "Sra.",
         "Dr."
      ],
      "suffix": [
         "Jr.",
         "Neto",
         "Filho"
      ]
   },
   "phone_number": {
      "formats": [
         "2########",
         "3########",
         "9########",
         "+351 2########",
         "+351 3########",
         "+351 9########"
      ]
   }
}